setup.py
pycnic/__init__.py
pycnic/cli.py
pycnic/core.py
pycnic/data.py
pycnic/errors.py
pycnic/utils.py
pycnic.egg-info/PKG-INFO
pycnic.egg-info/SOURCES.txt
pycnic.egg-info/dependency_links.txt
pycnic.egg-info/entry_points.txt
pycnic.egg-info/top_level.txt