Metadata-Version: 1.1
Name: pycnic
Version: 0.1.9
Summary: A simple, ultra light-weight, pure-python RESTful JSON API framework.
Home-page: http://pycnic.nullism.com
Author: Aaron Meier
Author-email: webgovernor@gmail.com
License: MIT
Platform: UNKNOWN
Provides: pycnic
